drex/__init__.py
drex/schedulers/algorithm1.py
drex/schedulers/algorithm2.py
drex/schedulers/algorithm3.py
drex/schedulers/random.py
drex/utils/__init__.py
drex/utils/load_data.py
drex/utils/poibin.py
drex/utils/tool_functions.py
drex/utils/reliability/__init__.py
drex/utils/reliability/fragment_handler.py
drex/utils/reliability/ida.py
drex/utils/reliability/utils.py
drex-0.0.2434.dist-info/METADATA
drex-0.0.2434.dist-info/WHEEL
drex-0.0.2434.dist-info/top_level.txt
drex-0.0.2434.dist-info/RECORD
