Metadata-Version: 2.1
Name: drex
Version: 0.0.2434
Summary: DRex package
Author-email: "Maxime, Dante, Haochen" <dantsanc@pa.uc3m.es>
Classifier: Programming Language :: Python :: 3
Classifier: License :: OSI Approved :: MIT License
Classifier: Operating System :: OS Independent
Requires-Python: >=3.8
Requires-Dist: numpy
Requires-Dist: scipy
